{
    "cupons": [
        {
            "cod": "ELDORADO_30",
            "discount": 30
        },
        {
            "cod": "ELDORADO_40",
            "discount": 40
        },
        {
            "cod": "ELDORADO_50",
            "discount": 50
        }
    ],
    "itens": [
        {
            "codigo": "1",
            "nome": "Poção de vida",
            "categoria": "Consumiveis",
            "atributos": [
                {
                    "desc": ""
                },
                {
                    "desc": ""
                },
                {
                    "desc": ""
                }
            ],
            "preco": 10
        },
        {
            "codigo": "2",
            "nome": "Poção de vida",
            "categoria": "Consumiveis",
            "atributos": [
                {
                    "desc": ""
                },
                {
                    "desc": ""
                },
                {
                    "desc": ""
                }
            ],
            "preco": 20
        },
        {
            "codigo": "3",
            "nome": "Poção de vida",
            "categoria": "Consumiveis",
            "atributos": [
                {
                    "desc": ""
                },
                {
                    "desc": ""
                },
                {
                    "desc": ""
                }
            ],
            "preco": 30
        },
        {
            "codigo": "4",
            "nome": "Poção de vida",
            "categoria": "Consumiveis",
            "atributos": [
                {
                    "desc": ""
                },
                {
                    "desc": ""
                },
                {
                    "desc": ""
                }
            ],
            "preco": 0
        },
        {
            "codigo": "5",
            "nome": "Poção de vida",
            "categoria": "Consumiveis",
            "atributos": [
                {
                    "desc": ""
                },
                {
                    "desc": ""
                },
                {
                    "desc": ""
                }
            ],
            "preco": 0
        },
        {
            "codigo": "6",
            "nome": "Poção de vida",
            "categoria": "Consumiveis",
            "atributos": [
                {
                    "desc": ""
                },
                {
                    "desc": ""
                },
                {
                    "desc": ""
                }
            ],
            "preco": 0
        },
        {
            "codigo": "7",
            "nome": "Poção de vida",
            "categoria": "Consumiveis",
            "atributos": [
                {
                    "desc": ""
                },
                {
                    "desc": ""
                },
                {
                    "desc": ""
                }
            ],
            "preco": 0
        },
        {
            "codigo": "8",
            "nome": "Poção de vida",
            "categoria": "Consumiveis",
            "atributos": [
                {
                    "desc": ""
                },
                {
                    "desc": ""
                },
                {
                    "desc": ""
                }
            ],
            "preco": 0
        },
        {
            "codigo": "9",
            "nome": "Poção de vida",
            "categoria": "Consumiveis",
            "atributos": [
                {
                    "desc": ""
                },
                {
                    "desc": ""
                },
                {
                    "desc": ""
                }
            ],
            "preco": 0
        }
    ]
}